[{"id":34239,"oID":8,"a":"2247,08","r":1},{"id":34240,"oID":19,"a":"2703,10","r":1},{"id":34241,"oID":8,"a":"1508,52","r":1},{"id":34242,"oID":9,"a":"2173,99","r":1},{"id":34243,"oID":5,"a":"1773,33","r":1},{"id":34244,"oID":17,"a":"1140,11","r":1},{"id":34245,"oID":2,"a":"3159,21","r":1},{"id":34246,"oID":15,"a":"2437,23","r":1},{"id":34247,"oID":3,"a":"1307,94","r":1},{"id":34248,"oID":3,"a":"3434,48","r":1},{"id":34249,"oID":1,"a":"3789,55","r":1},{"id":34250,"oID":17,"a":"2199,65","r":1},{"id":34251,"oID":8,"a":"1622,01","r":1},{"id":34252,"oID":5,"a":"1545,49","r":1},{"id":34253,"oID":7,"a":"3353,41","r":1},{"id":34254,"oID":4,"a":"3234,02","r":1},{"id":34255,"oID":17,"a":"3099,89","r":1},{"id":34256,"oID":17,"a":"1073,57","r":1},{"id":34257,"oID":16,"a":"2949,06","r":1},{"id":34258,"oID":12,"a":"3405,05","r":1},{"id":34259,"oID":2,"a":"2480,80","r":1},{"id":34260,"oID":19,"a":"2445,47","r":1},{"id":34261,"oID":8,"a":"1795,41","r":1},{"id":34262,"oID":18,"a":"2912,72","r":1},{"id":34263,"oID":4,"a":"1984,68","r":1},{"id":34264,"oID":15,"a":"1438,64","r":1},{"id":34265,"oID":12,"a":"2792,95","r":1},{"id":34266,"oID":11,"a":"3495,27","r":1},{"id":34267,"oID":17,"a":"2201,80","r":1},{"id":34268,"oID":20,"a":"1132,90","r":1},{"id":34269,"oID":10,"a":"2910,62","r":1},{"id":34270,"oID":16,"a":"1637,56","r":1},{"id":34271,"oID":8,"a":"3404,27","r":1},{"id":34272,"oID":12,"a":"2859,60","r":1},{"id":34273,"oID":10,"a":"1962,87","r":1},{"id":34274,"oID":1,"a":"3214,27","r":1},{"id":34275,"oID":3,"a":"1723,63","r":1},{"id":34276,"oID":4,"a":"1828,25","r":1},{"id":34277,"oID":11,"a":"2479,66","r":1},{"id":34278,"oID":6,"a":"3098,91","r":1},{"id":34279,"oID":6,"a":"2679,80","r":1},{"id":34280,"oID":6,"a":"1598,56","r":1},{"id":34281,"oID":14,"a":"2012,73","r":1},{"id":34282,"oID":20,"a":"3489,44","r":1},{"id":34283,"oID":10,"a":"2744,71","r":1},{"id":34284,"oID":18,"a":"2135,62","r":1},{"id":34285,"oID":14,"a":"3417,33","r":1},{"id":34286,"oID":7,"a":"1999,18","r":1},{"id":34287,"oID":4,"a":"2821,55","r":1},{"id":34288,"oID":15,"a":"1534,78","r":1},{"id":34289,"oID":3,"a":"2167,65","r":1},{"id":34290,"oID":16,"a":"2256,40","r":1},{"id":34291,"oID":17,"a":"2764,49","r":1},{"id":34292,"oID":16,"a":"1851,17","r":1},{"id":34293,"oID":1,"a":"2520,81","r":1},{"id":34294,"oID":3,"a":"2503,15","r":1},{"id":34295,"oID":10,"a":"2068,16","r":1},{"id":34296,"oID":20,"a":"1973,79","r":1},{"id":34297,"oID":11,"a":"3128,42","r":1},{"id":34298,"oID":6,"a":"3403,79","r":1},{"id":34299,"oID":13,"a":"1877,78","r":1},{"id":34300,"oID":6,"a":"2536,69","r":1},{"id":34301,"oID":7,"a":"1689,55","r":1},{"id":34302,"oID":9,"a":"3561,78","r":1},{"id":34303,"oID":18,"a":"2775,42","r":1},{"id":34304,"oID":20,"a":"2824,40","r":1},{"id":34305,"oID":12,"a":"2858,06","r":1},{"id":34306,"oID":4,"a":"3347,82","r":1},{"id":34307,"oID":14,"a":"2219,45","r":2},{"id":34308,"oID":15,"a":"2064,42","r":2},{"id":34309,"oID":12,"a":"2316,08","r":2},{"id":34310,"oID":5,"a":"681,68","r":2},{"id":34311,"oID":14,"a":"1858,19","r":2},{"id":34312,"oID":12,"a":"1804,64","r":2},{"id":34313,"oID":20,"a":"2032,67","r":2},{"id":34314,"oID":10,"a":"1218,95","r":2},{"id":34315,"oID":5,"a":"2817,10","r":2},{"id":34316,"oID":5,"a":"1105,68","r":2},{"id":34317,"oID":11,"a":"1490,14","r":2},{"id":34318,"oID":9,"a":"2537,14","r":2},{"id":34319,"oID":13,"a":"2622,99","r":2},{"id":34320,"oID":7,"a":"2648,19","r":2},{"id":34321,"oID":18,"a":"2783,67","r":2},{"id":34322,"oID":13,"a":"3358,62","r":2},{"id":34323,"oID":17,"a":"3243,24","r":2},{"id":34324,"oID":1,"a":"2571,82","r":2},{"id":34325,"oID":1,"a":"1266,57","r":2},{"id":34326,"oID":1,"a":"1310,99","r":2},{"id":34327,"oID":4,"a":"1096,69","r":2},{"id":34328,"oID":5,"a":"3190,43","r":2},{"id":34329,"oID":3,"a":"2272,36","r":2},{"id":34330,"oID":19,"a":"2378,41","r":2},{"id":34331,"oID":19,"a":"1327,65","r":2},{"id":34332,"oID":11,"a":"3454,21","r":2},{"id":34333,"oID":19,"a":"1325,05","r":2},{"id":34334,"oID":5,"a":"2204,24","r":2},{"id":34335,"oID":1,"a":"1697,36","r":2},{"id":34336,"oID":7,"a":"1613,35","r":2},{"id":34337,"oID":6,"a":"3249,26","r":2},{"id":34338,"oID":12,"a":"1683,65","r":2},{"id":34339,"oID":9,"a":"3406,61","r":2},{"id":34340,"oID":12,"a":"2581,00","r":2},{"id":34341,"oID":15,"a":"1153,44","r":2},{"id":34342,"oID":5,"a":"2895,02","r":2},{"id":34343,"oID":3,"a":"857,40","r":2},{"id":34344,"oID":8,"a":"605,58","r":2},{"id":34345,"oID":18,"a":"3538,05","r":2},{"id":34346,"oID":6,"a":"1549,76","r":2},{"id":34347,"oID":9,"a":"2342,54","r":2},{"id":34348,"oID":7,"a":"3781,02","r":2},{"id":34349,"oID":20,"a":"3013,82","r":2},{"id":34350,"oID":9,"a":"3501,97","r":2},{"id":34351,"oID":14,"a":"2139,82","r":2},{"id":34352,"oID":2,"a":"2053,97","r":2},{"id":34353,"oID":10,"a":"2510,62","r":2},{"id":34354,"oID":15,"a":"3602,22","r":2},{"id":34355,"oID":19,"a":"2439,26","r":2},{"id":34356,"oID":5,"a":"2083,78","r":2},{"id":34357,"oID":17,"a":"2302,66","r":2},{"id":34358,"oID":11,"a":"3699,89","r":2},{"id":34359,"oID":13,"a":"2232,58","r":2},{"id":34360,"oID":10,"a":"2507,58","r":2},{"id":34361,"oID":18,"a":"2501,86","r":2},{"id":34362,"oID":17,"a":"2864,23","r":2},{"id":34363,"oID":11,"a":"1228,92","r":2},{"id":34364,"oID":2,"a":"3342,27","r":2},{"id":34365,"oID":19,"a":"2368,05","r":2},{"id":34366,"oID":16,"a":"3052,48","r":2},{"id":34367,"oID":19,"a":"2132,32","r":2},{"id":34368,"oID":4,"a":"3085,54","r":2},{"id":34369,"oID":2,"a":"2301,07","r":2},{"id":34370,"oID":3,"a":"3081,30","r":2},{"id":34371,"oID":17,"a":"2657,73","r":2},{"id":34372,"oID":7,"a":"3671,37","r":2},{"id":34373,"oID":8,"a":"1630,27","r":2},{"id":34374,"oID":3,"a":"2283,62","r":2},{"id":34375,"oID":18,"a":"2411,72","r":2},{"id":34376,"oID":20,"a":"3515,12","r":2},{"id":34377,"oID":1,"a":"2378,64","r":2},{"id":34378,"oID":20,"a":"1811,92","r":3},{"id":34379,"oID":19,"a":"1177,45","r":3},{"id":34380,"oID":13,"a":"3467,41","r":3},{"id":34381,"oID":15,"a":"3549,99","r":3},{"id":34382,"oID":13,"a":"2623,64","r":3},{"id":34383,"oID":2,"a":"1752,35","r":3},{"id":34384,"oID":4,"a":"1976,56","r":3},{"id":34385,"oID":16,"a":"2913,69","r":3},{"id":34386,"oID":5,"a":"3019,42","r":3},{"id":34387,"oID":19,"a":"1937,49","r":3},{"id":34388,"oID":14,"a":"1448,24","r":3},{"id":34389,"oID":5,"a":"2831,41","r":3},{"id":34390,"oID":12,"a":"2987,94","r":3},{"id":34391,"oID":8,"a":"2012,78","r":3},{"id":34392,"oID":11,"a":"1397,86","r":3},{"id":34393,"oID":6,"a":"3709,82","r":3},{"id":34394,"oID":8,"a":"1275,43","r":3},{"id":34395,"oID":13,"a":"3094,37","r":3},{"id":34396,"oID":16,"a":"3013,03","r":3},{"id":34397,"oID":6,"a":"1580,82","r":3},{"id":34398,"oID":2,"a":"3187,59","r":3},{"id":34399,"oID":4,"a":"1889,83","r":3},{"id":34400,"oID":13,"a":"2042,53","r":3},{"id":34401,"oID":1,"a":"3290,07","r":3},{"id":34402,"oID":11,"a":"2041,79","r":3},{"id":34403,"oID":19,"a":"1041,54","r":3},{"id":34404,"oID":3,"a":"1772,06","r":3},{"id":34405,"oID":11,"a":"2306,93","r":3},{"id":34406,"oID":18,"a":"2695,03","r":3},{"id":34407,"oID":12,"a":"1949,05","r":3},{"id":34408,"oID":12,"a":"3220,41","r":3},{"id":34409,"oID":5,"a":"1160,37","r":3},{"id":34410,"oID":6,"a":"1858,17","r":3},{"id":34411,"oID":4,"a":"3363,43","r":3},{"id":34412,"oID":6,"a":"2095,92","r":3},{"id":34413,"oID":2,"a":"1371,89","r":3},{"id":34414,"oID":17,"a":"3207,60","r":3},{"id":34415,"oID":10,"a":"3153,79","r":3},{"id":34416,"oID":7,"a":"3781,19","r":3},{"id":34417,"oID":16,"a":"1021,86","r":3},{"id":34418,"oID":10,"a":"2882,65","r":3},{"id":34419,"oID":13,"a":"2774,48","r":3},{"id":34420,"oID":5,"a":"1091,03","r":3},{"id":34421,"oID":16,"a":"1750,35","r":3},{"id":34422,"oID":19,"a":"2336,71","r":3},{"id":34423,"oID":14,"a":"1598,98","r":3},{"id":34424,"oID":3,"a":"2967,38","r":3},{"id":34425,"oID":8,"a":"2447,95","r":3},{"id":34426,"oID":14,"a":"2028,80","r":3},{"id":34427,"oID":18,"a":"1961,96","r":3},{"id":34428,"oID":20,"a":"3495,32","r":3},{"id":34429,"oID":14,"a":"2636,92","r":3},{"id":34430,"oID":8,"a":"2964,96","r":3},{"id":34431,"oID":17,"a":"1304,19","r":3},{"id":34432,"oID":15,"a":"3493,64","r":3},{"id":34433,"oID":1,"a":"2006,67","r":3},{"id":34434,"oID":8,"a":"1529,45","r":3},{"id":34435,"oID":7,"a":"2506,11","r":3},{"id":34436,"oID":2,"a":"2895,70","r":3},{"id":34437,"oID":16,"a":"2241,53","r":3},{"id":34438,"oID":3,"a":"3005,19","r":3},{"id":34439,"oID":4,"a":"2335,43","r":3},{"id":34440,"oID":13,"a":"2341,80","r":3},{"id":34441,"oID":18,"a":"2599,84","r":3},{"id":34442,"oID":15,"a":"2231,54","r":3},{"id":34443,"oID":5,"a":"1687,05","r":3},{"id":34444,"oID":1,"a":"2422,37","r":3},{"id":34445,"oID":19,"a":"2680,17","r":3},{"id":34446,"oID":20,"a":"2404,96","r":3},{"id":34447,"oID":11,"a":"1027,94","r":3},{"id":34448,"oID":9,"a":"3066,28","r":3}]